montagnekit/__init__.py
montagnekit-0.0.0.dist-info/LICENSE
montagnekit-0.0.0.dist-info/METADATA
montagnekit-0.0.0.dist-info/WHEEL
montagnekit-0.0.0.dist-info/top_level.txt
montagnekit-0.0.0.dist-info/RECORD
